pywikidata/__init__.py
pywikidata/attributes.py
pywikidata/config.py
pywikidata/entity.py
pywikidata/logger.py
pywikidata/utils.py
pywikidata-0.1.9.dist-info/LICENSE
pywikidata-0.1.9.dist-info/WHEEL
pywikidata-0.1.9.dist-info/METADATA
pywikidata-0.1.9.dist-info/RECORD
