Metadata-Version: 2.1
Name: pywikidata
Version: 0.1.9
Summary: Python Wrapper for Wikidata KG
License: MIT
Author: Mikhail Salnikov
Requires-Python: >=3.7,<4.0
Classifier: License :: OSI Approved :: MIT License
Classifier: Programming Language :: Python :: 3
Classifier: Programming Language :: Python :: 3.7
Classifier: Programming Language :: Python :: 3.8
Classifier: Programming Language :: Python :: 3.9
Classifier: Programming Language :: Python :: 3.10
Classifier: Programming Language :: Python :: 3.11
Requires-Dist: joblib (>=1.2.0,<2.0.0)
Requires-Dist: requests (>=2.28.2,<3.0.0)
